web_extractor/init.py
web_extractor/server.py
mcp_web_extractor_aj-0.1.1.dist-info/METADATA
mcp_web_extractor_aj-0.1.1.dist-info/WHEEL
mcp_web_extractor_aj-0.1.1.dist-info/entry_points.txt
mcp_web_extractor_aj-0.1.1.dist-info/top_level.txt
mcp_web_extractor_aj-0.1.1.dist-info/RECORD
