Metadata-Version: 2.4
Name: mcp-web-extractor-aj
Version: 0.1.1
Summary: MCP server that extracts content from web pages for LLMs
Author-email: Ajay Kumar <miniphantom09@gmail.com>
License: MIT
Classifier: Programming Language :: Python :: 3
Classifier: License :: OSI Approved :: MIT License
Classifier: Operating System :: OS Independent
Requires-Python: >=3.9
Requires-Dist: mcp>=1.2.0
Requires-Dist: requests
Requires-Dist: beautifulsoup4
